opsmodel/__init__.py
opsmodel/model.py
opsmodel-1.2.0.dist-info/METADATA
opsmodel-1.2.0.dist-info/WHEEL
opsmodel-1.2.0.dist-info/licenses/LICENSE
opsmodel-1.2.0.dist-info/RECORD
