Metadata-Version: 2.1
Name: opsmodel
Version: 1.2.0
Summary: A python library for creating openseespy models
Author-email: Okhtai Alizadeh Arasi <ok.programss@gmail.com>
License-File: LICENSE
Classifier: License :: OSI Approved :: MIT License
Classifier: Operating System :: Microsoft :: Windows
Classifier: Programming Language :: Python :: 3
Requires-Python: >=3.9
